datastore/cassandra_util.py
datastore/simple_cassandra_datastore.py
fastastra/fastastra.py
fastastra-0.1.38.dist-info/METADATA
fastastra-0.1.38.dist-info/WHEEL
fastastra-0.1.38.dist-info/entry_points.txt
fastastra-0.1.38.dist-info/RECORD
