Metadata-Version: 2.4
Name: fastastra
Version: 0.1.38
Requires-Python: >=3.10
Requires-Dist: agentd>=0.1.4
Requires-Dist: cassandra-driver>=3.28
Requires-Dist: loguru>=0.7.0
Requires-Dist: numpy>=1.24.2
Requires-Dist: pydantic>=2.7.4
Requires-Dist: python-dotenv>=1.0.1
Requires-Dist: python-fasthtml>=0.2.4
Requires-Dist: pyyaml>=6.0.1
Requires-Dist: tenacity>=8.2.1
Requires-Dist: uvicorn>=0.30.3
Provides-Extra: dev
Requires-Dist: pytest-asyncio>=0.20.3; extra == 'dev'
Requires-Dist: pytest-cov>=4.0.0; extra == 'dev'
Requires-Dist: pytest>=7.2.1; extra == 'dev'
